{"dependencies":[{"name":"O:\\OneDrive\\Documents\\Learning\\WDS\\datepicker\\node_modules\\date-fns\\esm\\locale\\en-US\\package.json","includedInParent":true,"mtime":1635000531437},{"name":"O:\\OneDrive\\Documents\\Learning\\WDS\\datepicker\\package.json","includedInParent":true,"mtime":1635014046110},{"name":"../../../_lib/buildLocalizeFn/index.js","loc":{"line":1,"column":28},"parent":"O:\\OneDrive\\Documents\\Learning\\WDS\\datepicker\\node_modules\\date-fns\\esm\\locale\\en-US\\_lib\\localize\\index.js","resolved":"O:\\OneDrive\\Documents\\Learning\\WDS\\datepicker\\node_modules\\date-fns\\esm\\locale\\_lib\\buildLocalizeFn\\index.js"}],"generated":{"js":"\"use strict\";Object.defineProperty(exports,\"__esModule\",{value:!0});var n=require(\"../../../_lib/buildLocalizeFn/index.js\"),e=i(n);function i(n){return n&&n.__esModule?n:{default:n}}var t={narrow:[\"B\",\"A\"],abbreviated:[\"BC\",\"AD\"],wide:[\"Before Christ\",\"Anno Domini\"]},r={narrow:[\"1\",\"2\",\"3\",\"4\"],abbreviated:[\"Q1\",\"Q2\",\"Q3\",\"Q4\"],wide:[\"1st quarter\",\"2nd quarter\",\"3rd quarter\",\"4th quarter\"]},a={narrow:[\"J\",\"F\",\"M\",\"A\",\"M\",\"J\",\"J\",\"A\",\"S\",\"O\",\"N\",\"D\"],abbreviated:[\"Jan\",\"Feb\",\"Mar\",\"Apr\",\"May\",\"Jun\",\"Jul\",\"Aug\",\"Sep\",\"Oct\",\"Nov\",\"Dec\"],wide:[\"January\",\"February\",\"March\",\"April\",\"May\",\"June\",\"July\",\"August\",\"September\",\"October\",\"November\",\"December\"]},o={narrow:[\"S\",\"M\",\"T\",\"W\",\"T\",\"F\",\"S\"],short:[\"Su\",\"Mo\",\"Tu\",\"We\",\"Th\",\"Fr\",\"Sa\"],abbreviated:[\"Sun\",\"Mon\",\"Tue\",\"Wed\",\"Thu\",\"Fri\",\"Sat\"],wide:[\"Sunday\",\"Monday\",\"Tuesday\",\"Wednesday\",\"Thursday\",\"Friday\",\"Saturday\"]},d={narrow:{am:\"a\",pm:\"p\",midnight:\"mi\",noon:\"n\",morning:\"morning\",afternoon:\"afternoon\",evening:\"evening\",night:\"night\"},abbreviated:{am:\"AM\",pm:\"PM\",midnight:\"midnight\",noon:\"noon\",morning:\"morning\",afternoon:\"afternoon\",evening:\"evening\",night:\"night\"},wide:{am:\"a.m.\",pm:\"p.m.\",midnight:\"midnight\",noon:\"noon\",morning:\"morning\",afternoon:\"afternoon\",evening:\"evening\",night:\"night\"}},u={narrow:{am:\"a\",pm:\"p\",midnight:\"mi\",noon:\"n\",morning:\"in the morning\",afternoon:\"in the afternoon\",evening:\"in the evening\",night:\"at night\"},abbreviated:{am:\"AM\",pm:\"PM\",midnight:\"midnight\",noon:\"noon\",morning:\"in the morning\",afternoon:\"in the afternoon\",evening:\"in the evening\",night:\"at night\"},wide:{am:\"a.m.\",pm:\"p.m.\",midnight:\"midnight\",noon:\"noon\",morning:\"in the morning\",afternoon:\"in the afternoon\",evening:\"in the evening\",night:\"at night\"}},g=function(n,e){var i=Number(n),t=i%100;if(t>20||t<10)switch(t%10){case 1:return i+\"st\";case 2:return i+\"nd\";case 3:return i+\"rd\"}return i+\"th\"},m={ordinalNumber:g,era:(0,e.default)({values:t,defaultWidth:\"wide\"}),quarter:(0,e.default)({values:r,defaultWidth:\"wide\",argumentCallback:function(n){return n-1}}),month:(0,e.default)({values:a,defaultWidth:\"wide\"}),day:(0,e.default)({values:o,defaultWidth:\"wide\"}),dayPeriod:(0,e.default)({values:d,defaultWidth:\"wide\",formattingValues:u,defaultFormattingWidth:\"wide\"})};exports.default=m;","map":{"mappings":[{"source":"node_modules\\date-fns\\esm\\locale\\en-US\\_lib\\localize\\index.js","name":"localize","original":{"line":146,"column":15},"generated":{"line":1,"column":0}},{"source":"node_modules\\date-fns\\esm\\locale\\en-US\\_lib\\localize\\index.js","name":"localize","original":{"line":146,"column":15},"generated":{"line":1,"column":13}},{"source":"node_modules\\date-fns\\esm\\locale\\en-US\\_lib\\localize\\index.js","name":"localize","original":{"line":146,"column":15},"generated":{"line":1,"column":20}},{"source":"node_modules\\date-fns\\esm\\locale\\en-US\\_lib\\localize\\index.js","name":"localize","original":{"line":146,"column":15},"generated":{"line":1,"column":35}},{"source":"node_modules\\date-fns\\esm\\locale\\en-US\\_lib\\localize\\index.js","name":"localize","original":{"line":146,"column":15},"generated":{"line":1,"column":43}},{"source":"node_modules\\date-fns\\esm\\locale\\en-US\\_lib\\localize\\index.js","name":"localize","original":{"line":146,"column":15},"generated":{"line":1,"column":56}},{"source":"node_modules\\date-fns\\esm\\locale\\en-US\\_lib\\localize\\index.js","name":"localize","original":{"line":146,"column":15},"generated":{"line":1,"column":57}},{"source":"node_modules\\date-fns\\esm\\locale\\en-US\\_lib\\localize\\index.js","name":"localize","original":{"line":146,"column":15},"generated":{"line":1,"column":64}},{"source":"node_modules\\date-fns\\esm\\locale\\en-US\\_lib\\localize\\index.js","original":{"line":1,"column":0},"generated":{"line":1,"column":68}},{"source":"node_modules\\date-fns\\esm\\locale\\en-US\\_lib\\localize\\index.js","original":{"line":1,"column":0},"generated":{"line":1,"column":72}},{"source":"node_modules\\date-fns\\esm\\locale\\en-US\\_lib\\localize\\index.js","original":{"line":1,"column":0},"generated":{"line":1,"column":74}},{"source":"node_modules\\date-fns\\esm\\locale\\en-US\\_lib\\localize\\index.js","original":{"line":1,"column":0},"generated":{"line":1,"column":82}},{"source":"node_modules\\date-fns\\esm\\locale\\en-US\\_lib\\localize\\index.js","name":"localize","original":{"line":146,"column":15},"generated":{"line":1,"column":124}},{"source":"node_modules\\date-fns\\esm\\locale\\en-US\\_lib\\localize\\index.js","name":"localize","original":{"line":146,"column":15},"generated":{"line":1,"column":126}},{"source":"node_modules\\date-fns\\esm\\locale\\en-US\\_lib\\localize\\index.js","name":"localize","original":{"line":146,"column":15},"generated":{"line":1,"column":128}},{"source":"node_modules\\date-fns\\esm\\locale\\en-US\\_lib\\localize\\index.js","name":"localize","original":{"line":146,"column":15},"generated":{"line":1,"column":131}},{"source":"node_modules\\date-fns\\esm\\locale\\en-US\\_lib\\localize\\index.js","name":"localize","original":{"line":146,"column":15},"generated":{"line":1,"column":140}},{"source":"node_modules\\date-fns\\esm\\locale\\en-US\\_lib\\localize\\index.js","name":"localize","original":{"line":146,"column":15},"generated":{"line":1,"column":142}},{"source":"node_modules\\date-fns\\esm\\locale\\en-US\\_lib\\localize\\index.js","name":"localize","original":{"line":146,"column":15},"generated":{"line":1,"column":145}},{"source":"node_modules\\date-fns\\esm\\locale\\en-US\\_lib\\localize\\index.js","name":"localize","original":{"line":146,"column":15},"generated":{"line":1,"column":152}},{"source":"node_modules\\date-fns\\esm\\locale\\en-US\\_lib\\localize\\index.js","name":"localize","original":{"line":146,"column":15},"generated":{"line":1,"column":155}},{"source":"node_modules\\date-fns\\esm\\locale\\en-US\\_lib\\localize\\index.js","name":"localize","original":{"line":146,"column":15},"generated":{"line":1,"column":157}},{"source":"node_modules\\date-fns\\esm\\locale\\en-US\\_lib\\localize\\index.js","name":"localize","original":{"line":146,"column":15},"generated":{"line":1,"column":168}},{"source":"node_modules\\date-fns\\esm\\locale\\en-US\\_lib\\localize\\index.js","name":"localize","original":{"line":146,"column":15},"generated":{"line":1,"column":170}},{"source":"node_modules\\date-fns\\esm\\locale\\en-US\\_lib\\localize\\index.js","name":"localize","original":{"line":146,"column":15},"generated":{"line":1,"column":171}},{"source":"node_modules\\date-fns\\esm\\locale\\en-US\\_lib\\localize\\index.js","name":"localize","original":{"line":146,"column":15},"generated":{"line":1,"column":179}},{"source":"node_modules\\date-fns\\esm\\locale\\en-US\\_lib\\localize\\index.js","original":{"line":2,"column":0},"generated":{"line":1,"column":182}},{"source":"node_modules\\date-fns\\esm\\locale\\en-US\\_lib\\localize\\index.js","name":"eraValues","original":{"line":2,"column":4},"generated":{"line":1,"column":186}},{"source":"node_modules\\date-fns\\esm\\locale\\en-US\\_lib\\localize\\index.js","original":{"line":2,"column":16},"generated":{"line":1,"column":188}},{"source":"node_modules\\date-fns\\esm\\locale\\en-US\\_lib\\localize\\index.js","original":{"line":3,"column":10},"generated":{"line":1,"column":189}},{"source":"node_modules\\date-fns\\esm\\locale\\en-US\\_lib\\localize\\index.js","original":{"line":3,"column":10},"generated":{"line":1,"column":196}},{"source":"node_modules\\date-fns\\esm\\locale\\en-US\\_lib\\localize\\index.js","original":{"line":3,"column":11},"generated":{"line":1,"column":197}},{"source":"node_modules\\date-fns\\esm\\locale\\en-US\\_lib\\localize\\index.js","original":{"line":3,"column":16},"generated":{"line":1,"column":201}},{"source":"node_modules\\date-fns\\esm\\locale\\en-US\\_lib\\localize\\index.js","original":{"line":4,"column":15},"generated":{"line":1,"column":206}},{"source":"node_modules\\date-fns\\esm\\locale\\en-US\\_lib\\localize\\index.js","original":{"line":4,"column":15},"generated":{"line":1,"column":218}},{"source":"node_modules\\date-fns\\esm\\locale\\en-US\\_lib\\localize\\index.js","original":{"line":4,"column":16},"generated":{"line":1,"column":219}},{"source":"node_modules\\date-fns\\esm\\locale\\en-US\\_lib\\localize\\index.js","original":{"line":4,"column":22},"generated":{"line":1,"column":224}},{"source":"node_modules\\date-fns\\esm\\locale\\en-US\\_lib\\localize\\index.js","original":{"line":5,"column":8},"generated":{"line":1,"column":230}},{"source":"node_modules\\date-fns\\esm\\locale\\en-US\\_lib\\localize\\index.js","original":{"line":5,"column":8},"generated":{"line":1,"column":235}},{"source":"node_modules\\date-fns\\esm\\locale\\en-US\\_lib\\localize\\index.js","original":{"line":5,"column":9},"generated":{"line":1,"column":236}},{"source":"node_modules\\date-fns\\esm\\locale\\en-US\\_lib\\localize\\index.js","original":{"line":5,"column":26},"generated":{"line":1,"column":252}},{"source":"node_modules\\date-fns\\esm\\locale\\en-US\\_lib\\localize\\index.js","name":"quarterValues","original":{"line":7,"column":4},"generated":{"line":1,"column":268}},{"source":"node_modules\\date-fns\\esm\\locale\\en-US\\_lib\\localize\\index.js","original":{"line":7,"column":20},"generated":{"line":1,"column":270}},{"source":"node_modules\\date-fns\\esm\\locale\\en-US\\_lib\\localize\\index.js","original":{"line":8,"column":10},"generated":{"line":1,"column":271}},{"source":"node_modules\\date-fns\\esm\\locale\\en-US\\_lib\\localize\\index.js","original":{"line":8,"column":10},"generated":{"line":1,"column":278}},{"source":"node_modules\\date-fns\\esm\\locale\\en-US\\_lib\\localize\\index.js","original":{"line":8,"column":11},"generated":{"line":1,"column":279}},{"source":"node_modules\\date-fns\\esm\\locale\\en-US\\_lib\\localize\\index.js","original":{"line":8,"column":16},"generated":{"line":1,"column":283}},{"source":"node_modules\\date-fns\\esm\\locale\\en-US\\_lib\\localize\\index.js","original":{"line":8,"column":21},"generated":{"line":1,"column":287}},{"source":"node_modules\\date-fns\\esm\\locale\\en-US\\_lib\\localize\\index.js","original":{"line":8,"column":26},"generated":{"line":1,"column":291}},{"source":"node_modules\\date-fns\\esm\\locale\\en-US\\_lib\\localize\\index.js","original":{"line":9,"column":15},"generated":{"line":1,"column":296}},{"source":"node_modules\\date-fns\\esm\\locale\\en-US\\_lib\\localize\\index.js","original":{"line":9,"column":15},"generated":{"line":1,"column":308}},{"source":"node_modules\\date-fns\\esm\\locale\\en-US\\_lib\\localize\\index.js","original":{"line":9,"column":16},"generated":{"line":1,"column":309}},{"source":"node_modules\\date-fns\\esm\\locale\\en-US\\_lib\\localize\\index.js","original":{"line":9,"column":22},"generated":{"line":1,"column":314}},{"source":"node_modules\\date-fns\\esm\\locale\\en-US\\_lib\\localize\\index.js","original":{"line":9,"column":28},"generated":{"line":1,"column":319}},{"source":"node_modules\\date-fns\\esm\\locale\\en-US\\_lib\\localize\\index.js","original":{"line":9,"column":34},"generated":{"line":1,"column":324}},{"source":"node_modules\\date-fns\\esm\\locale\\en-US\\_lib\\localize\\index.js","original":{"line":10,"column":8},"generated":{"line":1,"column":330}},{"source":"node_modules\\date-fns\\esm\\locale\\en-US\\_lib\\localize\\index.js","original":{"line":10,"column":8},"generated":{"line":1,"column":335}},{"source":"node_modules\\date-fns\\esm\\locale\\en-US\\_lib\\localize\\index.js","original":{"line":10,"column":9},"generated":{"line":1,"column":336}},{"source":"node_modules\\date-fns\\esm\\locale\\en-US\\_lib\\localize\\index.js","original":{"line":10,"column":24},"generated":{"line":1,"column":350}},{"source":"node_modules\\date-fns\\esm\\locale\\en-US\\_lib\\localize\\index.js","original":{"line":10,"column":39},"generated":{"line":1,"column":364}},{"source":"node_modules\\date-fns\\esm\\locale\\en-US\\_lib\\localize\\index.js","original":{"line":10,"column":54},"generated":{"line":1,"column":378}},{"source":"node_modules\\date-fns\\esm\\locale\\en-US\\_lib\\localize\\index.js","name":"monthValues","original":{"line":16,"column":4},"generated":{"line":1,"column":394}},{"source":"node_modules\\date-fns\\esm\\locale\\en-US\\_lib\\localize\\index.js","original":{"line":16,"column":18},"generated":{"line":1,"column":396}},{"source":"node_modules\\date-fns\\esm\\locale\\en-US\\_lib\\localize\\index.js","original":{"line":17,"column":10},"generated":{"line":1,"column":397}},{"source":"node_modules\\date-fns\\esm\\locale\\en-US\\_lib\\localize\\index.js","original":{"line":17,"column":10},"generated":{"line":1,"column":404}},{"source":"node_modules\\date-fns\\esm\\locale\\en-US\\_lib\\localize\\index.js","original":{"line":17,"column":11},"generated":{"line":1,"column":405}},{"source":"node_modules\\date-fns\\esm\\locale\\en-US\\_lib\\localize\\index.js","original":{"line":17,"column":16},"generated":{"line":1,"column":409}},{"source":"node_modules\\date-fns\\esm\\locale\\en-US\\_lib\\localize\\index.js","original":{"line":17,"column":21},"generated":{"line":1,"column":413}},{"source":"node_modules\\date-fns\\esm\\locale\\en-US\\_lib\\localize\\index.js","original":{"line":17,"column":26},"generated":{"line":1,"column":417}},{"source":"node_modules\\date-fns\\esm\\locale\\en-US\\_lib\\localize\\index.js","original":{"line":17,"column":31},"generated":{"line":1,"column":421}},{"source":"node_modules\\date-fns\\esm\\locale\\en-US\\_lib\\localize\\index.js","original":{"line":17,"column":36},"generated":{"line":1,"column":425}},{"source":"node_modules\\date-fns\\esm\\locale\\en-US\\_lib\\localize\\index.js","original":{"line":17,"column":41},"generated":{"line":1,"column":429}},{"source":"node_modules\\date-fns\\esm\\locale\\en-US\\_lib\\localize\\index.js","original":{"line":17,"column":46},"generated":{"line":1,"column":433}},{"source":"node_modules\\date-fns\\esm\\locale\\en-US\\_lib\\localize\\index.js","original":{"line":17,"column":51},"generated":{"line":1,"column":437}},{"source":"node_modules\\date-fns\\esm\\locale\\en-US\\_lib\\localize\\index.js","original":{"line":17,"column":56},"generated":{"line":1,"column":441}},{"source":"node_modules\\date-fns\\esm\\locale\\en-US\\_lib\\localize\\index.js","original":{"line":17,"column":61},"generated":{"line":1,"column":445}},{"source":"node_modules\\date-fns\\esm\\locale\\en-US\\_lib\\localize\\index.js","original":{"line":17,"column":66},"generated":{"line":1,"column":449}},{"source":"node_modules\\date-fns\\esm\\locale\\en-US\\_lib\\localize\\index.js","original":{"line":18,"column":15},"generated":{"line":1,"column":454}},{"source":"node_modules\\date-fns\\esm\\locale\\en-US\\_lib\\localize\\index.js","original":{"line":18,"column":15},"generated":{"line":1,"column":466}},{"source":"node_modules\\date-fns\\esm\\locale\\en-US\\_lib\\localize\\index.js","original":{"line":18,"column":16},"generated":{"line":1,"column":467}},{"source":"node_modules\\date-fns\\esm\\locale\\en-US\\_lib\\localize\\index.js","original":{"line":18,"column":23},"generated":{"line":1,"column":473}},{"source":"node_modules\\date-fns\\esm\\locale\\en-US\\_lib\\localize\\index.js","original":{"line":18,"column":30},"generated":{"line":1,"column":479}},{"source":"node_modules\\date-fns\\esm\\locale\\en-US\\_lib\\localize\\index.js","original":{"line":18,"column":37},"generated":{"line":1,"column":485}},{"source":"node_modules\\date-fns\\esm\\locale\\en-US\\_lib\\localize\\index.js","original":{"line":18,"column":44},"generated":{"line":1,"column":491}},{"source":"node_modules\\date-fns\\esm\\locale\\en-US\\_lib\\localize\\index.js","original":{"line":18,"column":51},"generated":{"line":1,"column":497}},{"source":"node_modules\\date-fns\\esm\\locale\\en-US\\_lib\\localize\\index.js","original":{"line":18,"column":58},"generated":{"line":1,"column":503}},{"source":"node_modules\\date-fns\\esm\\locale\\en-US\\_lib\\localize\\index.js","original":{"line":18,"column":65},"generated":{"line":1,"column":509}},{"source":"node_modules\\date-fns\\esm\\locale\\en-US\\_lib\\localize\\index.js","original":{"line":18,"column":72},"generated":{"line":1,"column":515}},{"source":"node_modules\\date-fns\\esm\\locale\\en-US\\_lib\\localize\\index.js","original":{"line":18,"column":79},"generated":{"line":1,"column":521}},{"source":"node_modules\\date-fns\\esm\\locale\\en-US\\_lib\\localize\\index.js","original":{"line":18,"column":86},"generated":{"line":1,"column":527}},{"source":"node_modules\\date-fns\\esm\\locale\\en-US\\_lib\\localize\\index.js","original":{"line":18,"column":93},"generated":{"line":1,"column":533}},{"source":"node_modules\\date-fns\\esm\\locale\\en-US\\_lib\\localize\\index.js","original":{"line":19,"column":8},"generated":{"line":1,"column":540}},{"source":"node_modules\\date-fns\\esm\\locale\\en-US\\_lib\\localize\\index.js","original":{"line":19,"column":8},"generated":{"line":1,"column":545}},{"source":"node_modules\\date-fns\\esm\\locale\\en-US\\_lib\\localize\\index.js","original":{"line":19,"column":9},"generated":{"line":1,"column":546}},{"source":"node_modules\\date-fns\\esm\\locale\\en-US\\_lib\\localize\\index.js","original":{"line":19,"column":20},"generated":{"line":1,"column":556}},{"source":"node_modules\\date-fns\\esm\\locale\\en-US\\_lib\\localize\\index.js","original":{"line":19,"column":32},"generated":{"line":1,"column":567}},{"source":"node_modules\\date-fns\\esm\\locale\\en-US\\_lib\\localize\\index.js","original":{"line":19,"column":41},"generated":{"line":1,"column":575}},{"source":"node_modules\\date-fns\\esm\\locale\\en-US\\_lib\\localize\\index.js","original":{"line":19,"column":50},"generated":{"line":1,"column":583}},{"source":"node_modules\\date-fns\\esm\\locale\\en-US\\_lib\\localize\\index.js","original":{"line":19,"column":57},"generated":{"line":1,"column":589}},{"source":"node_modules\\date-fns\\esm\\locale\\en-US\\_lib\\localize\\index.js","original":{"line":19,"column":65},"generated":{"line":1,"column":596}},{"source":"node_modules\\date-fns\\esm\\locale\\en-US\\_lib\\localize\\index.js","original":{"line":19,"column":73},"generated":{"line":1,"column":603}},{"source":"node_modules\\date-fns\\esm\\locale\\en-US\\_lib\\localize\\index.js","original":{"line":19,"column":83},"generated":{"line":1,"column":612}},{"source":"node_modules\\date-fns\\esm\\locale\\en-US\\_lib\\localize\\index.js","original":{"line":19,"column":96},"generated":{"line":1,"column":624}},{"source":"node_modules\\date-fns\\esm\\locale\\en-US\\_lib\\localize\\index.js","original":{"line":19,"column":107},"generated":{"line":1,"column":634}},{"source":"node_modules\\date-fns\\esm\\locale\\en-US\\_lib\\localize\\index.js","original":{"line":19,"column":119},"generated":{"line":1,"column":645}},{"source":"node_modules\\date-fns\\esm\\locale\\en-US\\_lib\\localize\\index.js","name":"dayValues","original":{"line":21,"column":4},"generated":{"line":1,"column":658}},{"source":"node_modules\\date-fns\\esm\\locale\\en-US\\_lib\\localize\\index.js","original":{"line":21,"column":16},"generated":{"line":1,"column":660}},{"source":"node_modules\\date-fns\\esm\\locale\\en-US\\_lib\\localize\\index.js","original":{"line":22,"column":10},"generated":{"line":1,"column":661}},{"source":"node_modules\\date-fns\\esm\\locale\\en-US\\_lib\\localize\\index.js","original":{"line":22,"column":10},"generated":{"line":1,"column":668}},{"source":"node_modules\\date-fns\\esm\\locale\\en-US\\_lib\\localize\\index.js","original":{"line":22,"column":11},"generated":{"line":1,"column":669}},{"source":"node_modules\\date-fns\\esm\\locale\\en-US\\_lib\\localize\\index.js","original":{"line":22,"column":16},"generated":{"line":1,"column":673}},{"source":"node_modules\\date-fns\\esm\\locale\\en-US\\_lib\\localize\\index.js","original":{"line":22,"column":21},"generated":{"line":1,"column":677}},{"source":"node_modules\\date-fns\\esm\\locale\\en-US\\_lib\\localize\\index.js","original":{"line":22,"column":26},"generated":{"line":1,"column":681}},{"source":"node_modules\\date-fns\\esm\\locale\\en-US\\_lib\\localize\\index.js","original":{"line":22,"column":31},"generated":{"line":1,"column":685}},{"source":"node_modules\\date-fns\\esm\\locale\\en-US\\_lib\\localize\\index.js","original":{"line":22,"column":36},"generated":{"line":1,"column":689}},{"source":"node_modules\\date-fns\\esm\\locale\\en-US\\_lib\\localize\\index.js","original":{"line":22,"column":41},"generated":{"line":1,"column":693}},{"source":"node_modules\\date-fns\\esm\\locale\\en-US\\_lib\\localize\\index.js","original":{"line":23,"column":9},"generated":{"line":1,"column":698}},{"source":"node_modules\\date-fns\\esm\\locale\\en-US\\_lib\\localize\\index.js","original":{"line":23,"column":9},"generated":{"line":1,"column":704}},{"source":"node_modules\\date-fns\\esm\\locale\\en-US\\_lib\\localize\\index.js","original":{"line":23,"column":10},"generated":{"line":1,"column":705}},{"source":"node_modules\\date-fns\\esm\\locale\\en-US\\_lib\\localize\\index.js","original":{"line":23,"column":16},"generated":{"line":1,"column":710}},{"source":"node_modules\\date-fns\\esm\\locale\\en-US\\_lib\\localize\\index.js","original":{"line":23,"column":22},"generated":{"line":1,"column":715}},{"source":"node_modules\\date-fns\\esm\\locale\\en-US\\_lib\\localize\\index.js","original":{"line":23,"column":28},"generated":{"line":1,"column":720}},{"source":"node_modules\\date-fns\\esm\\locale\\en-US\\_lib\\localize\\index.js","original":{"line":23,"column":34},"generated":{"line":1,"column":725}},{"source":"node_modules\\date-fns\\esm\\locale\\en-US\\_lib\\localize\\index.js","original":{"line":23,"column":40},"generated":{"line":1,"column":730}},{"source":"node_modules\\date-fns\\esm\\locale\\en-US\\_lib\\localize\\index.js","original":{"line":23,"column":46},"generated":{"line":1,"column":735}},{"source":"node_modules\\date-fns\\esm\\locale\\en-US\\_lib\\localize\\index.js","original":{"line":24,"column":15},"generated":{"line":1,"column":741}},{"source":"node_modules\\date-fns\\esm\\locale\\en-US\\_lib\\localize\\index.js","original":{"line":24,"column":15},"generated":{"line":1,"column":753}},{"source":"node_modules\\date-fns\\esm\\locale\\en-US\\_lib\\localize\\index.js","original":{"line":24,"column":16},"generated":{"line":1,"column":754}},{"source":"node_modules\\date-fns\\esm\\locale\\en-US\\_lib\\localize\\index.js","original":{"line":24,"column":23},"generated":{"line":1,"column":760}},{"source":"node_modules\\date-fns\\esm\\locale\\en-US\\_lib\\localize\\index.js","original":{"line":24,"column":30},"generated":{"line":1,"column":766}},{"source":"node_modules\\date-fns\\esm\\locale\\en-US\\_lib\\localize\\index.js","original":{"line":24,"column":37},"generated":{"line":1,"column":772}},{"source":"node_modules\\date-fns\\esm\\locale\\en-US\\_lib\\localize\\index.js","original":{"line":24,"column":44},"generated":{"line":1,"column":778}},{"source":"node_modules\\date-fns\\esm\\locale\\en-US\\_lib\\localize\\index.js","original":{"line":24,"column":51},"generated":{"line":1,"column":784}},{"source":"node_modules\\date-fns\\esm\\locale\\en-US\\_lib\\localize\\index.js","original":{"line":24,"column":58},"generated":{"line":1,"column":790}},{"source":"node_modules\\date-fns\\esm\\locale\\en-US\\_lib\\localize\\index.js","original":{"line":25,"column":8},"generated":{"line":1,"column":797}},{"source":"node_modules\\date-fns\\esm\\locale\\en-US\\_lib\\localize\\index.js","original":{"line":25,"column":8},"generated":{"line":1,"column":802}},{"source":"node_modules\\date-fns\\esm\\locale\\en-US\\_lib\\localize\\index.js","original":{"line":25,"column":9},"generated":{"line":1,"column":803}},{"source":"node_modules\\date-fns\\esm\\locale\\en-US\\_lib\\localize\\index.js","original":{"line":25,"column":19},"generated":{"line":1,"column":812}},{"source":"node_modules\\date-fns\\esm\\locale\\en-US\\_lib\\localize\\index.js","original":{"line":25,"column":29},"generated":{"line":1,"column":821}},{"source":"node_modules\\date-fns\\esm\\locale\\en-US\\_lib\\localize\\index.js","original":{"line":25,"column":40},"generated":{"line":1,"column":831}},{"source":"node_modules\\date-fns\\esm\\locale\\en-US\\_lib\\localize\\index.js","original":{"line":25,"column":53},"generated":{"line":1,"column":843}},{"source":"node_modules\\date-fns\\esm\\locale\\en-US\\_lib\\localize\\index.js","original":{"line":25,"column":65},"generated":{"line":1,"column":854}},{"source":"node_modules\\date-fns\\esm\\locale\\en-US\\_lib\\localize\\index.js","original":{"line":25,"column":75},"generated":{"line":1,"column":863}},{"source":"node_modules\\date-fns\\esm\\locale\\en-US\\_lib\\localize\\index.js","name":"dayPeriodValues","original":{"line":27,"column":4},"generated":{"line":1,"column":876}},{"source":"node_modules\\date-fns\\esm\\locale\\en-US\\_lib\\localize\\index.js","original":{"line":27,"column":22},"generated":{"line":1,"column":878}},{"source":"node_modules\\date-fns\\esm\\locale\\en-US\\_lib\\localize\\index.js","original":{"line":28,"column":10},"generated":{"line":1,"column":879}},{"source":"node_modules\\date-fns\\esm\\locale\\en-US\\_lib\\localize\\index.js","original":{"line":28,"column":10},"generated":{"line":1,"column":886}},{"source":"node_modules\\date-fns\\esm\\locale\\en-US\\_lib\\localize\\index.js","original":{"line":29,"column":8},"generated":{"line":1,"column":887}},{"source":"node_modules\\date-fns\\esm\\locale\\en-US\\_lib\\localize\\index.js","original":{"line":29,"column":8},"generated":{"line":1,"column":890}},{"source":"node_modules\\date-fns\\esm\\locale\\en-US\\_lib\\localize\\index.js","original":{"line":30,"column":8},"generated":{"line":1,"column":894}},{"source":"node_modules\\date-fns\\esm\\locale\\en-US\\_lib\\localize\\index.js","original":{"line":30,"column":8},"generated":{"line":1,"column":897}},{"source":"node_modules\\date-fns\\esm\\locale\\en-US\\_lib\\localize\\index.js","original":{"line":31,"column":14},"generated":{"line":1,"column":901}},{"source":"node_modules\\date-fns\\esm\\locale\\en-US\\_lib\\localize\\index.js","original":{"line":31,"column":14},"generated":{"line":1,"column":910}},{"source":"node_modules\\date-fns\\esm\\locale\\en-US\\_lib\\localize\\index.js","original":{"line":32,"column":10},"generated":{"line":1,"column":915}},{"source":"node_modules\\date-fns\\esm\\locale\\en-US\\_lib\\localize\\index.js","original":{"line":32,"column":10},"generated":{"line":1,"column":920}},{"source":"node_modules\\date-fns\\esm\\locale\\en-US\\_lib\\localize\\index.js","original":{"line":33,"column":13},"generated":{"line":1,"column":924}},{"source":"node_modules\\date-fns\\esm\\locale\\en-US\\_lib\\localize\\index.js","original":{"line":33,"column":13},"generated":{"line":1,"column":932}},{"source":"node_modules\\date-fns\\esm\\locale\\en-US\\_lib\\localize\\index.js","original":{"line":34,"column":15},"generated":{"line":1,"column":942}},{"source":"node_modules\\date-fns\\esm\\locale\\en-US\\_lib\\localize\\index.js","original":{"line":34,"column":15},"generated":{"line":1,"column":952}},{"source":"node_modules\\date-fns\\esm\\locale\\en-US\\_lib\\localize\\index.js","original":{"line":35,"column":13},"generated":{"line":1,"column":964}},{"source":"node_modules\\date-fns\\esm\\locale\\en-US\\_lib\\localize\\index.js","original":{"line":35,"column":13},"generated":{"line":1,"column":972}},{"source":"node_modules\\date-fns\\esm\\locale\\en-US\\_lib\\localize\\index.js","original":{"line":36,"column":11},"generated":{"line":1,"column":982}},{"source":"node_modules\\date-fns\\esm\\locale\\en-US\\_lib\\localize\\index.js","original":{"line":36,"column":11},"generated":{"line":1,"column":988}},{"source":"node_modules\\date-fns\\esm\\locale\\en-US\\_lib\\localize\\index.js","original":{"line":38,"column":15},"generated":{"line":1,"column":997}},{"source":"node_modules\\date-fns\\esm\\locale\\en-US\\_lib\\localize\\index.js","original":{"line":38,"column":15},"generated":{"line":1,"column":1009}},{"source":"node_modules\\date-fns\\esm\\locale\\en-US\\_lib\\localize\\index.js","original":{"line":39,"column":8},"generated":{"line":1,"column":1010}},{"source":"node_modules\\date-fns\\esm\\locale\\en-US\\_lib\\localize\\index.js","original":{"line":39,"column":8},"generated":{"line":1,"column":1013}},{"source":"node_modules\\date-fns\\esm\\locale\\en-US\\_lib\\localize\\index.js","original":{"line":40,"column":8},"generated":{"line":1,"column":1018}},{"source":"node_modules\\date-fns\\esm\\locale\\en-US\\_lib\\localize\\index.js","original":{"line":40,"column":8},"generated":{"line":1,"column":1021}},{"source":"node_modules\\date-fns\\esm\\locale\\en-US\\_lib\\localize\\index.js","original":{"line":41,"column":14},"generated":{"line":1,"column":1026}},{"source":"node_modules\\date-fns\\esm\\locale\\en-US\\_lib\\localize\\index.js","original":{"line":41,"column":14},"generated":{"line":1,"column":1035}},{"source":"node_modules\\date-fns\\esm\\locale\\en-US\\_lib\\localize\\index.js","original":{"line":42,"column":10},"generated":{"line":1,"column":1046}},{"source":"node_modules\\date-fns\\esm\\locale\\en-US\\_lib\\localize\\index.js","original":{"line":42,"column":10},"generated":{"line":1,"column":1051}},{"source":"node_modules\\date-fns\\esm\\locale\\en-US\\_lib\\localize\\index.js","original":{"line":43,"column":13},"generated":{"line":1,"column":1058}},{"source":"node_modules\\date-fns\\esm\\locale\\en-US\\_lib\\localize\\index.js","original":{"line":43,"column":13},"generated":{"line":1,"column":1066}},{"source":"node_modules\\date-fns\\esm\\locale\\en-US\\_lib\\localize\\index.js","original":{"line":44,"column":15},"generated":{"line":1,"column":1076}},{"source":"node_modules\\date-fns\\esm\\locale\\en-US\\_lib\\localize\\index.js","original":{"line":44,"column":15},"generated":{"line":1,"column":1086}},{"source":"node_modules\\date-fns\\esm\\locale\\en-US\\_lib\\localize\\index.js","original":{"line":45,"column":13},"generated":{"line":1,"column":1098}},{"source":"node_modules\\date-fns\\esm\\locale\\en-US\\_lib\\localize\\index.js","original":{"line":45,"column":13},"generated":{"line":1,"column":1106}},{"source":"node_modules\\date-fns\\esm\\locale\\en-US\\_lib\\localize\\index.js","original":{"line":46,"column":11},"generated":{"line":1,"column":1116}},{"source":"node_modules\\date-fns\\esm\\locale\\en-US\\_lib\\localize\\index.js","original":{"line":46,"column":11},"generated":{"line":1,"column":1122}},{"source":"node_modules\\date-fns\\esm\\locale\\en-US\\_lib\\localize\\index.js","original":{"line":48,"column":8},"generated":{"line":1,"column":1131}},{"source":"node_modules\\date-fns\\esm\\locale\\en-US\\_lib\\localize\\index.js","original":{"line":48,"column":8},"generated":{"line":1,"column":1136}},{"source":"node_modules\\date-fns\\esm\\locale\\en-US\\_lib\\localize\\index.js","original":{"line":49,"column":8},"generated":{"line":1,"column":1137}},{"source":"node_modules\\date-fns\\esm\\locale\\en-US\\_lib\\localize\\index.js","original":{"line":49,"column":8},"generated":{"line":1,"column":1140}},{"source":"node_modules\\date-fns\\esm\\locale\\en-US\\_lib\\localize\\index.js","original":{"line":50,"column":8},"generated":{"line":1,"column":1147}},{"source":"node_modules\\date-fns\\esm\\locale\\en-US\\_lib\\localize\\index.js","original":{"line":50,"column":8},"generated":{"line":1,"column":1150}},{"source":"node_modules\\date-fns\\esm\\locale\\en-US\\_lib\\localize\\index.js","original":{"line":51,"column":14},"generated":{"line":1,"column":1157}},{"source":"node_modules\\date-fns\\esm\\locale\\en-US\\_lib\\localize\\index.js","original":{"line":51,"column":14},"generated":{"line":1,"column":1166}},{"source":"node_modules\\date-fns\\esm\\locale\\en-US\\_lib\\localize\\index.js","original":{"line":52,"column":10},"generated":{"line":1,"column":1177}},{"source":"node_modules\\date-fns\\esm\\locale\\en-US\\_lib\\localize\\index.js","original":{"line":52,"column":10},"generated":{"line":1,"column":1182}},{"source":"node_modules\\date-fns\\esm\\locale\\en-US\\_lib\\localize\\index.js","original":{"line":53,"column":13},"generated":{"line":1,"column":1189}},{"source":"node_modules\\date-fns\\esm\\locale\\en-US\\_lib\\localize\\index.js","original":{"line":53,"column":13},"generated":{"line":1,"column":1197}},{"source":"node_modules\\date-fns\\esm\\locale\\en-US\\_lib\\localize\\index.js","original":{"line":54,"column":15},"generated":{"line":1,"column":1207}},{"source":"node_modules\\date-fns\\esm\\locale\\en-US\\_lib\\localize\\index.js","original":{"line":54,"column":15},"generated":{"line":1,"column":1217}},{"source":"node_modules\\date-fns\\esm\\locale\\en-US\\_lib\\localize\\index.js","original":{"line":55,"column":13},"generated":{"line":1,"column":1229}},{"source":"node_modules\\date-fns\\esm\\locale\\en-US\\_lib\\localize\\index.js","original":{"line":55,"column":13},"generated":{"line":1,"column":1237}},{"source":"node_modules\\date-fns\\esm\\locale\\en-US\\_lib\\localize\\index.js","original":{"line":56,"column":11},"generated":{"line":1,"column":1247}},{"source":"node_modules\\date-fns\\esm\\locale\\en-US\\_lib\\localize\\index.js","original":{"line":56,"column":11},"generated":{"line":1,"column":1253}},{"source":"node_modules\\date-fns\\esm\\locale\\en-US\\_lib\\localize\\index.js","name":"formattingDayPeriodValues","original":{"line":59,"column":4},"generated":{"line":1,"column":1263}},{"source":"node_modules\\date-fns\\esm\\locale\\en-US\\_lib\\localize\\index.js","original":{"line":59,"column":32},"generated":{"line":1,"column":1265}},{"source":"node_modules\\date-fns\\esm\\locale\\en-US\\_lib\\localize\\index.js","original":{"line":60,"column":10},"generated":{"line":1,"column":1266}},{"source":"node_modules\\date-fns\\esm\\locale\\en-US\\_lib\\localize\\index.js","original":{"line":60,"column":10},"generated":{"line":1,"column":1273}},{"source":"node_modules\\date-fns\\esm\\locale\\en-US\\_lib\\localize\\index.js","original":{"line":61,"column":8},"generated":{"line":1,"column":1274}},{"source":"node_modules\\date-fns\\esm\\locale\\en-US\\_lib\\localize\\index.js","original":{"line":61,"column":8},"generated":{"line":1,"column":1277}},{"source":"node_modules\\date-fns\\esm\\locale\\en-US\\_lib\\localize\\index.js","original":{"line":62,"column":8},"generated":{"line":1,"column":1281}},{"source":"node_modules\\date-fns\\esm\\locale\\en-US\\_lib\\localize\\index.js","original":{"line":62,"column":8},"generated":{"line":1,"column":1284}},{"source":"node_modules\\date-fns\\esm\\locale\\en-US\\_lib\\localize\\index.js","original":{"line":63,"column":14},"generated":{"line":1,"column":1288}},{"source":"node_modules\\date-fns\\esm\\locale\\en-US\\_lib\\localize\\index.js","original":{"line":63,"column":14},"generated":{"line":1,"column":1297}},{"source":"node_modules\\date-fns\\esm\\locale\\en-US\\_lib\\localize\\index.js","original":{"line":64,"column":10},"generated":{"line":1,"column":1302}},{"source":"node_modules\\date-fns\\esm\\locale\\en-US\\_lib\\localize\\index.js","original":{"line":64,"column":10},"generated":{"line":1,"column":1307}},{"source":"node_modules\\date-fns\\esm\\locale\\en-US\\_lib\\localize\\index.js","original":{"line":65,"column":13},"generated":{"line":1,"column":1311}},{"source":"node_modules\\date-fns\\esm\\locale\\en-US\\_lib\\localize\\index.js","original":{"line":65,"column":13},"generated":{"line":1,"column":1319}},{"source":"node_modules\\date-fns\\esm\\locale\\en-US\\_lib\\localize\\index.js","original":{"line":66,"column":15},"generated":{"line":1,"column":1336}},{"source":"node_modules\\date-fns\\esm\\locale\\en-US\\_lib\\localize\\index.js","original":{"line":66,"column":15},"generated":{"line":1,"column":1346}},{"source":"node_modules\\date-fns\\esm\\locale\\en-US\\_lib\\localize\\index.js","original":{"line":67,"column":13},"generated":{"line":1,"column":1365}},{"source":"node_modules\\date-fns\\esm\\locale\\en-US\\_lib\\localize\\index.js","original":{"line":67,"column":13},"generated":{"line":1,"column":1373}},{"source":"node_modules\\date-fns\\esm\\locale\\en-US\\_lib\\localize\\index.js","original":{"line":68,"column":11},"generated":{"line":1,"column":1390}},{"source":"node_modules\\date-fns\\esm\\locale\\en-US\\_lib\\localize\\index.js","original":{"line":68,"column":11},"generated":{"line":1,"column":1396}},{"source":"node_modules\\date-fns\\esm\\locale\\en-US\\_lib\\localize\\index.js","original":{"line":70,"column":15},"generated":{"line":1,"column":1408}},{"source":"node_modules\\date-fns\\esm\\locale\\en-US\\_lib\\localize\\index.js","original":{"line":70,"column":15},"generated":{"line":1,"column":1420}},{"source":"node_modules\\date-fns\\esm\\locale\\en-US\\_lib\\localize\\index.js","original":{"line":71,"column":8},"generated":{"line":1,"column":1421}},{"source":"node_modules\\date-fns\\esm\\locale\\en-US\\_lib\\localize\\index.js","original":{"line":71,"column":8},"generated":{"line":1,"column":1424}},{"source":"node_modules\\date-fns\\esm\\locale\\en-US\\_lib\\localize\\index.js","original":{"line":72,"column":8},"generated":{"line":1,"column":1429}},{"source":"node_modules\\date-fns\\esm\\locale\\en-US\\_lib\\localize\\index.js","original":{"line":72,"column":8},"generated":{"line":1,"column":1432}},{"source":"node_modules\\date-fns\\esm\\locale\\en-US\\_lib\\localize\\index.js","original":{"line":73,"column":14},"generated":{"line":1,"column":1437}},{"source":"node_modules\\date-fns\\esm\\locale\\en-US\\_lib\\localize\\index.js","original":{"line":73,"column":14},"generated":{"line":1,"column":1446}},{"source":"node_modules\\date-fns\\esm\\locale\\en-US\\_lib\\localize\\index.js","original":{"line":74,"column":10},"generated":{"line":1,"column":1457}},{"source":"node_modules\\date-fns\\esm\\locale\\en-US\\_lib\\localize\\index.js","original":{"line":74,"column":10},"generated":{"line":1,"column":1462}},{"source":"node_modules\\date-fns\\esm\\locale\\en-US\\_lib\\localize\\index.js","original":{"line":75,"column":13},"generated":{"line":1,"column":1469}},{"source":"node_modules\\date-fns\\esm\\locale\\en-US\\_lib\\localize\\index.js","original":{"line":75,"column":13},"generated":{"line":1,"column":1477}},{"source":"node_modules\\date-fns\\esm\\locale\\en-US\\_lib\\localize\\index.js","original":{"line":76,"column":15},"generated":{"line":1,"column":1494}},{"source":"node_modules\\date-fns\\esm\\locale\\en-US\\_lib\\localize\\index.js","original":{"line":76,"column":15},"generated":{"line":1,"column":1504}},{"source":"node_modules\\date-fns\\esm\\locale\\en-US\\_lib\\localize\\index.js","original":{"line":77,"column":13},"generated":{"line":1,"column":1523}},{"source":"node_modules\\date-fns\\esm\\locale\\en-US\\_lib\\localize\\index.js","original":{"line":77,"column":13},"generated":{"line":1,"column":1531}},{"source":"node_modules\\date-fns\\esm\\locale\\en-US\\_lib\\localize\\index.js","original":{"line":78,"column":11},"generated":{"line":1,"column":1548}},{"source":"node_modules\\date-fns\\esm\\locale\\en-US\\_lib\\localize\\index.js","original":{"line":78,"column":11},"generated":{"line":1,"column":1554}},{"source":"node_modules\\date-fns\\esm\\locale\\en-US\\_lib\\localize\\index.js","original":{"line":80,"column":8},"generated":{"line":1,"column":1566}},{"source":"node_modules\\date-fns\\esm\\locale\\en-US\\_lib\\localize\\index.js","original":{"line":80,"column":8},"generated":{"line":1,"column":1571}},{"source":"node_modules\\date-fns\\esm\\locale\\en-US\\_lib\\localize\\index.js","original":{"line":81,"column":8},"generated":{"line":1,"column":1572}},{"source":"node_modules\\date-fns\\esm\\locale\\en-US\\_lib\\localize\\index.js","original":{"line":81,"column":8},"generated":{"line":1,"column":1575}},{"source":"node_modules\\date-fns\\esm\\locale\\en-US\\_lib\\localize\\index.js","original":{"line":82,"column":8},"generated":{"line":1,"column":1582}},{"source":"node_modules\\date-fns\\esm\\locale\\en-US\\_lib\\localize\\index.js","original":{"line":82,"column":8},"generated":{"line":1,"column":1585}},{"source":"node_modules\\date-fns\\esm\\locale\\en-US\\_lib\\localize\\index.js","original":{"line":83,"column":14},"generated":{"line":1,"column":1592}},{"source":"node_modules\\date-fns\\esm\\locale\\en-US\\_lib\\localize\\index.js","original":{"line":83,"column":14},"generated":{"line":1,"column":1601}},{"source":"node_modules\\date-fns\\esm\\locale\\en-US\\_lib\\localize\\index.js","original":{"line":84,"column":10},"generated":{"line":1,"column":1612}},{"source":"node_modules\\date-fns\\esm\\locale\\en-US\\_lib\\localize\\index.js","original":{"line":84,"column":10},"generated":{"line":1,"column":1617}},{"source":"node_modules\\date-fns\\esm\\locale\\en-US\\_lib\\localize\\index.js","original":{"line":85,"column":13},"generated":{"line":1,"column":1624}},{"source":"node_modules\\date-fns\\esm\\locale\\en-US\\_lib\\localize\\index.js","original":{"line":85,"column":13},"generated":{"line":1,"column":1632}},{"source":"node_modules\\date-fns\\esm\\locale\\en-US\\_lib\\localize\\index.js","original":{"line":86,"column":15},"generated":{"line":1,"column":1649}},{"source":"node_modules\\date-fns\\esm\\locale\\en-US\\_lib\\localize\\index.js","original":{"line":86,"column":15},"generated":{"line":1,"column":1659}},{"source":"node_modules\\date-fns\\esm\\locale\\en-US\\_lib\\localize\\index.js","original":{"line":87,"column":13},"generated":{"line":1,"column":1678}},{"source":"node_modules\\date-fns\\esm\\locale\\en-US\\_lib\\localize\\index.js","original":{"line":87,"column":13},"generated":{"line":1,"column":1686}},{"source":"node_modules\\date-fns\\esm\\locale\\en-US\\_lib\\localize\\index.js","original":{"line":88,"column":11},"generated":{"line":1,"column":1703}},{"source":"node_modules\\date-fns\\esm\\locale\\en-US\\_lib\\localize\\index.js","original":{"line":88,"column":11},"generated":{"line":1,"column":1709}},{"source":"node_modules\\date-fns\\esm\\locale\\en-US\\_lib\\localize\\index.js","name":"ordinalNumber","original":{"line":92,"column":4},"generated":{"line":1,"column":1722}},{"source":"node_modules\\date-fns\\esm\\locale\\en-US\\_lib\\localize\\index.js","original":{"line":92,"column":20},"generated":{"line":1,"column":1724}},{"source":"node_modules\\date-fns\\esm\\locale\\en-US\\_lib\\localize\\index.js","name":"dirtyNumber","original":{"line":92,"column":30},"generated":{"line":1,"column":1733}},{"source":"node_modules\\date-fns\\esm\\locale\\en-US\\_lib\\localize\\index.js","name":"_options","original":{"line":92,"column":43},"generated":{"line":1,"column":1735}},{"source":"node_modules\\date-fns\\esm\\locale\\en-US\\_lib\\localize\\index.js","name":"number","original":{"line":93,"column":6},"generated":{"line":1,"column":1738}},{"source":"node_modules\\date-fns\\esm\\locale\\en-US\\_lib\\localize\\index.js","name":"number","original":{"line":93,"column":6},"generated":{"line":1,"column":1742}},{"source":"node_modules\\date-fns\\esm\\locale\\en-US\\_lib\\localize\\index.js","name":"Number","original":{"line":93,"column":15},"generated":{"line":1,"column":1744}},{"source":"node_modules\\date-fns\\esm\\locale\\en-US\\_lib\\localize\\index.js","name":"dirtyNumber","original":{"line":93,"column":22},"generated":{"line":1,"column":1751}},{"source":"node_modules\\date-fns\\esm\\locale\\en-US\\_lib\\localize\\index.js","name":"rem100","original":{"line":100,"column":6},"generated":{"line":1,"column":1754}},{"source":"node_modules\\date-fns\\esm\\locale\\en-US\\_lib\\localize\\index.js","name":"number","original":{"line":100,"column":15},"generated":{"line":1,"column":1756}},{"source":"node_modules\\date-fns\\esm\\locale\\en-US\\_lib\\localize\\index.js","original":{"line":100,"column":24},"generated":{"line":1,"column":1758}},{"source":"node_modules\\date-fns\\esm\\locale\\en-US\\_lib\\localize\\index.js","name":"rem100","original":{"line":102,"column":6},"generated":{"line":1,"column":1762}},{"source":"node_modules\\date-fns\\esm\\locale\\en-US\\_lib\\localize\\index.js","name":"rem100","original":{"line":102,"column":6},"generated":{"line":1,"column":1765}},{"source":"node_modules\\date-fns\\esm\\locale\\en-US\\_lib\\localize\\index.js","original":{"line":102,"column":15},"generated":{"line":1,"column":1767}},{"source":"node_modules\\date-fns\\esm\\locale\\en-US\\_lib\\localize\\index.js","name":"rem100","original":{"line":102,"column":21},"generated":{"line":1,"column":1771}},{"source":"node_modules\\date-fns\\esm\\locale\\en-US\\_lib\\localize\\index.js","original":{"line":102,"column":30},"generated":{"line":1,"column":1773}},{"source":"node_modules\\date-fns\\esm\\locale\\en-US\\_lib\\localize\\index.js","name":"rem100","original":{"line":103,"column":12},"generated":{"line":1,"column":1776}},{"source":"node_modules\\date-fns\\esm\\locale\\en-US\\_lib\\localize\\index.js","name":"rem100","original":{"line":103,"column":12},"generated":{"line":1,"column":1783}},{"source":"node_modules\\date-fns\\esm\\locale\\en-US\\_lib\\localize\\index.js","original":{"line":103,"column":21},"generated":{"line":1,"column":1785}},{"source":"node_modules\\date-fns\\esm\\locale\\en-US\\_lib\\localize\\index.js","original":{"line":104,"column":11},"generated":{"line":1,"column":1789}},{"source":"node_modules\\date-fns\\esm\\locale\\en-US\\_lib\\localize\\index.js","original":{"line":104,"column":11},"generated":{"line":1,"column":1794}},{"source":"node_modules\\date-fns\\esm\\locale\\en-US\\_lib\\localize\\index.js","name":"number","original":{"line":105,"column":15},"generated":{"line":1,"column":1796}},{"source":"node_modules\\date-fns\\esm\\locale\\en-US\\_lib\\localize\\index.js","name":"number","original":{"line":105,"column":15},"generated":{"line":1,"column":1803}},{"source":"node_modules\\date-fns\\esm\\locale\\en-US\\_lib\\localize\\index.js","original":{"line":105,"column":24},"generated":{"line":1,"column":1805}},{"source":"node_modules\\date-fns\\esm\\locale\\en-US\\_lib\\localize\\index.js","original":{"line":107,"column":11},"generated":{"line":1,"column":1810}},{"source":"node_modules\\date-fns\\esm\\locale\\en-US\\_lib\\localize\\index.js","original":{"line":107,"column":11},"generated":{"line":1,"column":1815}},{"source":"node_modules\\date-fns\\esm\\locale\\en-US\\_lib\\localize\\index.js","name":"number","original":{"line":108,"column":15},"generated":{"line":1,"column":1817}},{"source":"node_modules\\date-fns\\esm\\locale\\en-US\\_lib\\localize\\index.js","name":"number","original":{"line":108,"column":15},"generated":{"line":1,"column":1824}},{"source":"node_modules\\date-fns\\esm\\locale\\en-US\\_lib\\localize\\index.js","original":{"line":108,"column":24},"generated":{"line":1,"column":1826}},{"source":"node_modules\\date-fns\\esm\\locale\\en-US\\_lib\\localize\\index.js","original":{"line":110,"column":11},"generated":{"line":1,"column":1831}},{"source":"node_modules\\date-fns\\esm\\locale\\en-US\\_lib\\localize\\index.js","original":{"line":110,"column":11},"generated":{"line":1,"column":1836}},{"source":"node_modules\\date-fns\\esm\\locale\\en-US\\_lib\\localize\\index.js","name":"number","original":{"line":111,"column":15},"generated":{"line":1,"column":1838}},{"source":"node_modules\\date-fns\\esm\\locale\\en-US\\_lib\\localize\\index.js","name":"number","original":{"line":111,"column":15},"generated":{"line":1,"column":1845}},{"source":"node_modules\\date-fns\\esm\\locale\\en-US\\_lib\\localize\\index.js","original":{"line":111,"column":24},"generated":{"line":1,"column":1847}},{"source":"node_modules\\date-fns\\esm\\locale\\en-US\\_lib\\localize\\index.js","name":"number","original":{"line":115,"column":9},"generated":{"line":1,"column":1852}},{"source":"node_modules\\date-fns\\esm\\locale\\en-US\\_lib\\localize\\index.js","name":"number","original":{"line":115,"column":9},"generated":{"line":1,"column":1859}},{"source":"node_modules\\date-fns\\esm\\locale\\en-US\\_lib\\localize\\index.js","original":{"line":115,"column":18},"generated":{"line":1,"column":1861}},{"source":"node_modules\\date-fns\\esm\\locale\\en-US\\_lib\\localize\\index.js","name":"localize","original":{"line":118,"column":4},"generated":{"line":1,"column":1867}},{"source":"node_modules\\date-fns\\esm\\locale\\en-US\\_lib\\localize\\index.js","original":{"line":118,"column":15},"generated":{"line":1,"column":1869}},{"source":"node_modules\\date-fns\\esm\\locale\\en-US\\_lib\\localize\\index.js","name":"ordinalNumber","original":{"line":119,"column":17},"generated":{"line":1,"column":1870}},{"source":"node_modules\\date-fns\\esm\\locale\\en-US\\_lib\\localize\\index.js","name":"ordinalNumber","original":{"line":119,"column":17},"generated":{"line":1,"column":1884}},{"source":"node_modules\\date-fns\\esm\\locale\\en-US\\_lib\\localize\\index.js","original":{"line":120,"column":7},"generated":{"line":1,"column":1886}},{"source":"node_modules\\date-fns\\esm\\locale\\en-US\\_lib\\localize\\index.js","original":{"line":120,"column":7},"generated":{"line":1,"column":1891}},{"source":"node_modules\\date-fns\\esm\\locale\\en-US\\_lib\\localize\\index.js","original":{"line":120,"column":23},"generated":{"line":1,"column":1893}},{"source":"node_modules\\date-fns\\esm\\locale\\en-US\\_lib\\localize\\index.js","original":{"line":120,"column":23},"generated":{"line":1,"column":1895}},{"source":"node_modules\\date-fns\\esm\\locale\\en-US\\_lib\\localize\\index.js","original":{"line":120,"column":23},"generated":{"line":1,"column":1904}},{"source":"node_modules\\date-fns\\esm\\locale\\en-US\\_lib\\localize\\index.js","name":"eraValues","original":{"line":121,"column":12},"generated":{"line":1,"column":1905}},{"source":"node_modules\\date-fns\\esm\\locale\\en-US\\_lib\\localize\\index.js","name":"eraValues","original":{"line":121,"column":12},"generated":{"line":1,"column":1912}},{"source":"node_modules\\date-fns\\esm\\locale\\en-US\\_lib\\localize\\index.js","original":{"line":122,"column":18},"generated":{"line":1,"column":1914}},{"source":"node_modules\\date-fns\\esm\\locale\\en-US\\_lib\\localize\\index.js","original":{"line":122,"column":18},"generated":{"line":1,"column":1927}},{"source":"node_modules\\date-fns\\esm\\locale\\en-US\\_lib\\localize\\index.js","original":{"line":124,"column":11},"generated":{"line":1,"column":1936}},{"source":"node_modules\\date-fns\\esm\\locale\\en-US\\_lib\\localize\\index.js","original":{"line":124,"column":11},"generated":{"line":1,"column":1945}},{"source":"node_modules\\date-fns\\esm\\locale\\en-US\\_lib\\localize\\index.js","original":{"line":124,"column":27},"generated":{"line":1,"column":1947}},{"source":"node_modules\\date-fns\\esm\\locale\\en-US\\_lib\\localize\\index.js","original":{"line":124,"column":27},"generated":{"line":1,"column":1949}},{"source":"node_modules\\date-fns\\esm\\locale\\en-US\\_lib\\localize\\index.js","original":{"line":124,"column":27},"generated":{"line":1,"column":1958}},{"source":"node_modules\\date-fns\\esm\\locale\\en-US\\_lib\\localize\\index.js","name":"quarterValues","original":{"line":125,"column":12},"generated":{"line":1,"column":1959}},{"source":"node_modules\\date-fns\\esm\\locale\\en-US\\_lib\\localize\\index.js","name":"quarterValues","original":{"line":125,"column":12},"generated":{"line":1,"column":1966}},{"source":"node_modules\\date-fns\\esm\\locale\\en-US\\_lib\\localize\\index.js","original":{"line":126,"column":18},"generated":{"line":1,"column":1968}},{"source":"node_modules\\date-fns\\esm\\locale\\en-US\\_lib\\localize\\index.js","original":{"line":126,"column":18},"generated":{"line":1,"column":1981}},{"source":"node_modules\\date-fns\\esm\\locale\\en-US\\_lib\\localize\\index.js","original":{"line":127,"column":22},"generated":{"line":1,"column":1988}},{"source":"node_modules\\date-fns\\esm\\locale\\en-US\\_lib\\localize\\index.js","original":{"line":127,"column":22},"generated":{"line":1,"column":2005}},{"source":"node_modules\\date-fns\\esm\\locale\\en-US\\_lib\\localize\\index.js","name":"quarter","original":{"line":127,"column":32},"generated":{"line":1,"column":2014}},{"source":"node_modules\\date-fns\\esm\\locale\\en-US\\_lib\\localize\\index.js","name":"quarter","original":{"line":128,"column":13},"generated":{"line":1,"column":2017}},{"source":"node_modules\\date-fns\\esm\\locale\\en-US\\_lib\\localize\\index.js","name":"quarter","original":{"line":128,"column":13},"generated":{"line":1,"column":2024}},{"source":"node_modules\\date-fns\\esm\\locale\\en-US\\_lib\\localize\\index.js","original":{"line":128,"column":23},"generated":{"line":1,"column":2026}},{"source":"node_modules\\date-fns\\esm\\locale\\en-US\\_lib\\localize\\index.js","original":{"line":131,"column":9},"generated":{"line":1,"column":2031}},{"source":"node_modules\\date-fns\\esm\\locale\\en-US\\_lib\\localize\\index.js","original":{"line":131,"column":9},"generated":{"line":1,"column":2038}},{"source":"node_modules\\date-fns\\esm\\locale\\en-US\\_lib\\localize\\index.js","original":{"line":131,"column":25},"generated":{"line":1,"column":2040}},{"source":"node_modules\\date-fns\\esm\\locale\\en-US\\_lib\\localize\\index.js","original":{"line":131,"column":25},"generated":{"line":1,"column":2042}},{"source":"node_modules\\date-fns\\esm\\locale\\en-US\\_lib\\localize\\index.js","original":{"line":131,"column":25},"generated":{"line":1,"column":2051}},{"source":"node_modules\\date-fns\\esm\\locale\\en-US\\_lib\\localize\\index.js","name":"monthValues","original":{"line":132,"column":12},"generated":{"line":1,"column":2052}},{"source":"node_modules\\date-fns\\esm\\locale\\en-US\\_lib\\localize\\index.js","name":"monthValues","original":{"line":132,"column":12},"generated":{"line":1,"column":2059}},{"source":"node_modules\\date-fns\\esm\\locale\\en-US\\_lib\\localize\\index.js","original":{"line":133,"column":18},"generated":{"line":1,"column":2061}},{"source":"node_modules\\date-fns\\esm\\locale\\en-US\\_lib\\localize\\index.js","original":{"line":133,"column":18},"generated":{"line":1,"column":2074}},{"source":"node_modules\\date-fns\\esm\\locale\\en-US\\_lib\\localize\\index.js","original":{"line":135,"column":7},"generated":{"line":1,"column":2083}},{"source":"node_modules\\date-fns\\esm\\locale\\en-US\\_lib\\localize\\index.js","original":{"line":135,"column":7},"generated":{"line":1,"column":2088}},{"source":"node_modules\\date-fns\\esm\\locale\\en-US\\_lib\\localize\\index.js","original":{"line":135,"column":23},"generated":{"line":1,"column":2090}},{"source":"node_modules\\date-fns\\esm\\locale\\en-US\\_lib\\localize\\index.js","original":{"line":135,"column":23},"generated":{"line":1,"column":2092}},{"source":"node_modules\\date-fns\\esm\\locale\\en-US\\_lib\\localize\\index.js","original":{"line":135,"column":23},"generated":{"line":1,"column":2101}},{"source":"node_modules\\date-fns\\esm\\locale\\en-US\\_lib\\localize\\index.js","name":"dayValues","original":{"line":136,"column":12},"generated":{"line":1,"column":2102}},{"source":"node_modules\\date-fns\\esm\\locale\\en-US\\_lib\\localize\\index.js","name":"dayValues","original":{"line":136,"column":12},"generated":{"line":1,"column":2109}},{"source":"node_modules\\date-fns\\esm\\locale\\en-US\\_lib\\localize\\index.js","original":{"line":137,"column":18},"generated":{"line":1,"column":2111}},{"source":"node_modules\\date-fns\\esm\\locale\\en-US\\_lib\\localize\\index.js","original":{"line":137,"column":18},"generated":{"line":1,"column":2124}},{"source":"node_modules\\date-fns\\esm\\locale\\en-US\\_lib\\localize\\index.js","original":{"line":139,"column":13},"generated":{"line":1,"column":2133}},{"source":"node_modules\\date-fns\\esm\\locale\\en-US\\_lib\\localize\\index.js","original":{"line":139,"column":13},"generated":{"line":1,"column":2144}},{"source":"node_modules\\date-fns\\esm\\locale\\en-US\\_lib\\localize\\index.js","original":{"line":139,"column":29},"generated":{"line":1,"column":2146}},{"source":"node_modules\\date-fns\\esm\\locale\\en-US\\_lib\\localize\\index.js","original":{"line":139,"column":29},"generated":{"line":1,"column":2148}},{"source":"node_modules\\date-fns\\esm\\locale\\en-US\\_lib\\localize\\index.js","original":{"line":139,"column":29},"generated":{"line":1,"column":2157}},{"source":"node_modules\\date-fns\\esm\\locale\\en-US\\_lib\\localize\\index.js","name":"dayPeriodValues","original":{"line":140,"column":12},"generated":{"line":1,"column":2158}},{"source":"node_modules\\date-fns\\esm\\locale\\en-US\\_lib\\localize\\index.js","name":"dayPeriodValues","original":{"line":140,"column":12},"generated":{"line":1,"column":2165}},{"source":"node_modules\\date-fns\\esm\\locale\\en-US\\_lib\\localize\\index.js","original":{"line":141,"column":18},"generated":{"line":1,"column":2167}},{"source":"node_modules\\date-fns\\esm\\locale\\en-US\\_lib\\localize\\index.js","original":{"line":141,"column":18},"generated":{"line":1,"column":2180}},{"source":"node_modules\\date-fns\\esm\\locale\\en-US\\_lib\\localize\\index.js","name":"formattingDayPeriodValues","original":{"line":142,"column":22},"generated":{"line":1,"column":2187}},{"source":"node_modules\\date-fns\\esm\\locale\\en-US\\_lib\\localize\\index.js","name":"formattingDayPeriodValues","original":{"line":142,"column":22},"generated":{"line":1,"column":2204}},{"source":"node_modules\\date-fns\\esm\\locale\\en-US\\_lib\\localize\\index.js","original":{"line":143,"column":28},"generated":{"line":1,"column":2206}},{"source":"node_modules\\date-fns\\esm\\locale\\en-US\\_lib\\localize\\index.js","original":{"line":143,"column":28},"generated":{"line":1,"column":2229}},{"source":"node_modules\\date-fns\\esm\\locale\\en-US\\_lib\\localize\\index.js","name":"localize","original":{"line":146,"column":15},"generated":{"line":1,"column":2239}},{"source":"node_modules\\date-fns\\esm\\locale\\en-US\\_lib\\localize\\index.js","name":"localize","original":{"line":146,"column":15},"generated":{"line":1,"column":2247}},{"source":"node_modules\\date-fns\\esm\\locale\\en-US\\_lib\\localize\\index.js","name":"localize","original":{"line":146,"column":15},"generated":{"line":1,"column":2255}}],"sources":{"node_modules\\date-fns\\esm\\locale\\en-US\\_lib\\localize\\index.js":"import buildLocalizeFn from \"../../../_lib/buildLocalizeFn/index.js\";\nvar eraValues = {\n  narrow: ['B', 'A'],\n  abbreviated: ['BC', 'AD'],\n  wide: ['Before Christ', 'Anno Domini']\n};\nvar quarterValues = {\n  narrow: ['1', '2', '3', '4'],\n  abbreviated: ['Q1', 'Q2', 'Q3', 'Q4'],\n  wide: ['1st quarter', '2nd quarter', '3rd quarter', '4th quarter']\n}; // Note: in English, the names of days of the week and months are capitalized.\n// If you are making a new locale based on this one, check if the same is true for the language you're working on.\n// Generally, formatted dates should look like they are in the middle of a sentence,\n// e.g. in Spanish language the weekdays and months should be in the lowercase.\n\nvar monthValues = {\n  narrow: ['J', 'F', 'M', 'A', 'M', 'J', 'J', 'A', 'S', 'O', 'N', 'D'],\n  abbreviated: ['Jan', 'Feb', 'Mar', 'Apr', 'May', 'Jun', 'Jul', 'Aug', 'Sep', 'Oct', 'Nov', 'Dec'],\n  wide: ['January', 'February', 'March', 'April', 'May', 'June', 'July', 'August', 'September', 'October', 'November', 'December']\n};\nvar dayValues = {\n  narrow: ['S', 'M', 'T', 'W', 'T', 'F', 'S'],\n  short: ['Su', 'Mo', 'Tu', 'We', 'Th', 'Fr', 'Sa'],\n  abbreviated: ['Sun', 'Mon', 'Tue', 'Wed', 'Thu', 'Fri', 'Sat'],\n  wide: ['Sunday', 'Monday', 'Tuesday', 'Wednesday', 'Thursday', 'Friday', 'Saturday']\n};\nvar dayPeriodValues = {\n  narrow: {\n    am: 'a',\n    pm: 'p',\n    midnight: 'mi',\n    noon: 'n',\n    morning: 'morning',\n    afternoon: 'afternoon',\n    evening: 'evening',\n    night: 'night'\n  },\n  abbreviated: {\n    am: 'AM',\n    pm: 'PM',\n    midnight: 'midnight',\n    noon: 'noon',\n    morning: 'morning',\n    afternoon: 'afternoon',\n    evening: 'evening',\n    night: 'night'\n  },\n  wide: {\n    am: 'a.m.',\n    pm: 'p.m.',\n    midnight: 'midnight',\n    noon: 'noon',\n    morning: 'morning',\n    afternoon: 'afternoon',\n    evening: 'evening',\n    night: 'night'\n  }\n};\nvar formattingDayPeriodValues = {\n  narrow: {\n    am: 'a',\n    pm: 'p',\n    midnight: 'mi',\n    noon: 'n',\n    morning: 'in the morning',\n    afternoon: 'in the afternoon',\n    evening: 'in the evening',\n    night: 'at night'\n  },\n  abbreviated: {\n    am: 'AM',\n    pm: 'PM',\n    midnight: 'midnight',\n    noon: 'noon',\n    morning: 'in the morning',\n    afternoon: 'in the afternoon',\n    evening: 'in the evening',\n    night: 'at night'\n  },\n  wide: {\n    am: 'a.m.',\n    pm: 'p.m.',\n    midnight: 'midnight',\n    noon: 'noon',\n    morning: 'in the morning',\n    afternoon: 'in the afternoon',\n    evening: 'in the evening',\n    night: 'at night'\n  }\n};\n\nvar ordinalNumber = function (dirtyNumber, _options) {\n  var number = Number(dirtyNumber); // If ordinal numbers depend on context, for example,\n  // if they are different for different grammatical genders,\n  // use `options.unit`.\n  //\n  // `unit` can be 'year', 'quarter', 'month', 'week', 'date', 'dayOfYear',\n  // 'day', 'hour', 'minute', 'second'.\n\n  var rem100 = number % 100;\n\n  if (rem100 > 20 || rem100 < 10) {\n    switch (rem100 % 10) {\n      case 1:\n        return number + 'st';\n\n      case 2:\n        return number + 'nd';\n\n      case 3:\n        return number + 'rd';\n    }\n  }\n\n  return number + 'th';\n};\n\nvar localize = {\n  ordinalNumber: ordinalNumber,\n  era: buildLocalizeFn({\n    values: eraValues,\n    defaultWidth: 'wide'\n  }),\n  quarter: buildLocalizeFn({\n    values: quarterValues,\n    defaultWidth: 'wide',\n    argumentCallback: function (quarter) {\n      return quarter - 1;\n    }\n  }),\n  month: buildLocalizeFn({\n    values: monthValues,\n    defaultWidth: 'wide'\n  }),\n  day: buildLocalizeFn({\n    values: dayValues,\n    defaultWidth: 'wide'\n  }),\n  dayPeriod: buildLocalizeFn({\n    values: dayPeriodValues,\n    defaultWidth: 'wide',\n    formattingValues: formattingDayPeriodValues,\n    defaultFormattingWidth: 'wide'\n  })\n};\nexport default localize;"},"lineCount":null}},"hash":"902de5bf6db53f3d717920b3d7c17b75","cacheData":{"env":{}},"id":502}